sky/__init__.py
michaelvll_skypilot-0.0.2.dist-info/LICENSE
michaelvll_skypilot-0.0.2.dist-info/METADATA
michaelvll_skypilot-0.0.2.dist-info/WHEEL
michaelvll_skypilot-0.0.2.dist-info/entry_points.txt
michaelvll_skypilot-0.0.2.dist-info/top_level.txt
michaelvll_skypilot-0.0.2.dist-info/RECORD
