Metadata-Version: 2.1
Name: michaelvll-skypilot
Version: 0.0.2
Summary: An intercloud broker above the cloud
License: Apache License
Project-URL: Homepage, https://sky-proj-sky.readthedocs-hosted.com/en/latest/
Classifier: Programming Language :: Python :: 3
Classifier: License :: OSI Approved :: Apache Software License
Classifier: Operating System :: OS Independent
Requires-Python: >=3.6
License-File: LICENSE
Requires-Dist: wheel
Requires-Dist: Click
Requires-Dist: colorama
Requires-Dist: cryptography
Requires-Dist: jinja2
Requires-Dist: jsonschema
Requires-Dist: networkx
Requires-Dist: oauth2client
Requires-Dist: pandas
Requires-Dist: pycryptodome (==3.12.0)
Requires-Dist: pendulum
Requires-Dist: PrettyTable
Requires-Dist: ray[default] (>=1.9.0)
Requires-Dist: rich
Requires-Dist: tabulate
Requires-Dist: filelock
Requires-Dist: grpcio (<=1.43.0)
Requires-Dist: protobuf (<4.0.0)
Requires-Dist: psutil
Requires-Dist: pulp
Provides-Extra: all
Requires-Dist: awscli ; extra == 'all'
Requires-Dist: boto3 ; extra == 'all'
Requires-Dist: azure-cli (==2.30.0) ; extra == 'all'
Requires-Dist: google-api-python-client ; extra == 'all'
Requires-Dist: google-cloud-storage ; extra == 'all'
Requires-Dist: docker ; extra == 'all'
Provides-Extra: aws
Requires-Dist: awscli ; extra == 'aws'
Requires-Dist: boto3 ; extra == 'aws'
Provides-Extra: azure
Requires-Dist: azure-cli (==2.30.0) ; extra == 'azure'
Provides-Extra: docker
Requires-Dist: docker ; extra == 'docker'
Provides-Extra: gcp
Requires-Dist: google-api-python-client ; extra == 'gcp'
Requires-Dist: google-cloud-storage ; extra == 'gcp'
